better_proxy/__init__.py
better_proxy/proxy.py
better_proxy-1.3.1.dist-info/METADATA
better_proxy-1.3.1.dist-info/WHEEL
better_proxy-1.3.1.dist-info/RECORD
