Metadata-Version: 2.1
Name: better-proxy
Version: 1.3.1
Summary: Better proxy!
Home-page: https://github.com/alenkimov/better_proxy
Author: Alen
Author-email: alen.kimov@gmail.com
Requires-Python: >=3.8,<4.0
Classifier: Programming Language :: Python :: 3
Classifier: Programming Language :: Python :: 3.8
Classifier: Programming Language :: Python :: 3.9
Classifier: Programming Language :: Python :: 3.10
Classifier: Programming Language :: Python :: 3.11
Classifier: Programming Language :: Python :: 3.12
Requires-Dist: pydantic (>=2)
Project-URL: Repository, https://github.com/alenkimov/better_proxy
Project-URL: Source, https://github.com/alenkimov/better_proxy
